pyqol/All.py
pyqol/Bittors.py
pyqol/CORE.py
pyqol/FP.py
pyqol/ML.py
pyqol/Structs.py
pyqol/__init__.py
pyqol-0.1.1.0.dist-info/LICENSE
pyqol-0.1.1.0.dist-info/METADATA
pyqol-0.1.1.0.dist-info/WHEEL
pyqol-0.1.1.0.dist-info/top_level.txt
pyqol-0.1.1.0.dist-info/RECORD
