Metadata-Version: 2.1
Name: pyqol
Version: 0.1.1.0
Summary: A Pack of useful python QoL changes
Home-page: https://maxime.codes/Libraries/
Author: Maxime
Author-email: emixampons@gmail.com
License: UNKNOWN
Platform: UNKNOWN
Classifier: Programming Language :: Python :: 3
Classifier: License :: OSI Approved :: MIT License
Requires-Python: >=3.6
Requires-Dist: fastcore
